{"standardid":903817,"title":"Ao\u00fbt 1914","imageposter":"img\/aout_1914.jpg","backdrop":"bg\/aout_1914_bg.jpg","yearofproduction":2014,"directors":["Fedrik De Beul"],"actors":["Patrick Descamps","Fabrizio Rongione","Guido De Craene","Florian Vigilante"],"synopsisshort":"Augustus 1914. Door valse geruchten ontstaan bloedbaden die tot paniek leiden: \"Alle Belgen zijn sluipschutters.\" Een voorzichtige burgemeester beveelt dat alle wapens verzameld moeten worden en dat alle honden moeten worden gedood. ","mainlanguage":"Frans","genre":"Actiefilm\/thriller","propadult":false,"proplength":957,"kijkwijzer":64,"priority":2,"ranking":0,"popularity":0}